ocr_translate_google/__init__.py
ocr_translate_google/plugin.py
ocr_translate_google-0.3.0.dist-info/entry_points.txt
ocr_translate_google-0.3.0.dist-info/licenses/LICENSE.txt
ocr_translate_google-0.3.0.dist-info/WHEEL
ocr_translate_google-0.3.0.dist-info/METADATA
ocr_translate_google-0.3.0.dist-info/RECORD
