Metadata-Version: 2.4
Name: ocr_translate-google
Version: 0.3.0
Summary: Plugin to implement google translation for ocr_translate.
Keywords: django,translation
Author: Davide Grassano
Requires-Python: >=3.10
Classifier: Programming Language :: Python
Classifier: Programming Language :: Python :: 3.10
Classifier: Programming Language :: Python :: 3.11
Classifier: Programming Language :: Python :: 3.12
Classifier: Programming Language :: Python :: 3.13
Classifier: Natural Language :: English
Classifier: Topic :: Text Processing :: Linguistic
License-File: LICENSE.txt
Requires-Dist: django-ocr_translate>=0.7.0,<1.0
Requires-Dist: googletrans~=4.0.2
Requires-Dist: pre-commit ; extra == "pre-commit"
Requires-Dist: pylint ; extra == "pre-commit"
Requires-Dist: pylint-pytest ; extra == "pre-commit"
Requires-Dist: pylint-django ; extra == "pre-commit"
Requires-Dist: flit ; extra == "release"
Requires-Dist: pytest ; extra == "tests"
Requires-Dist: pytest-cov ; extra == "tests"
Requires-Dist: pytest-django ; extra == "tests"
Project-URL: Source, https://github.com/crivella/ocr_translate-google
Provides-Extra: pre-commit
Provides-Extra: release
Provides-Extra: tests
